{
	"topicsCategoryFilters" : {
		"none" : 0,
		"links" : 1,
		"questions" : 2,
		"answeredQuestions" : 4,
		"media" : 8,
		"textOnly" : 16,
		"announcement" : 32,
		"bungieOfficial" : 64,
		"polls" : 128,
		"0" : "none",
		"1" : "links",
		"2" : "questions",
		"4" : "answeredQuestions",
		"8" : "media",
		"16" : "textOnly",
		"32" : "announcement",
		"64" : "bungieOfficial",
		"128" : "polls"
	},
	"topicsQuickDate" : {
		"all" : 0,
		"lastYear" : 1,
		"lastMonth" : 2,
		"lastWeek" : 3,
		"lastDay" : 4,
		"0" : "all",
		"1" : "lastYear",
		"2" : "lastMonth",
		"3" : "lastWeek",
		"4" : "lastDay"
	},
	"topicsSort" : {
		"default" : 0,
		"lastReplied" : 1,
		"mostReplied" : 2,
		"popularity" : 3,
		"controversiality" : 4,
		"liked" : 5,
		"higghestRated" : 6, 
		"mostUpdvoted" : 7,
		"0" : "default",
		"1" : "lastReplied",
		"2" : "mostReplied",
		"3" : "popularity",
		"4" : "controversiality",
		"5" : "liked",
		"6" : "highestRated",
		"7" : "mostUpvoted"
	},
	"mediaType" : {
		"none" : 0,
		"image" : 1,
		"video" : 2,
		"youtube" : 3,
		"0" : "none",
		"1" : "image",
		"2" : "video",
		"3" : "youtube"
	},
	"postPopularity" : {
		"empty" : 0,
		"default" : 1,
		"discussed" : 2,
		"coolStory" : 3,
		"headtingUp" : 4,
		"hot" : 5,
		"0" : "empty",
		"1" : "default",
		"2" : "discussed",
		"3" : "coolStory",
		"4" : "heatingUp",
		"5" : "hot"	
	},
	"postCategory" : {
		"none" : 0,
		"textOnly" : 1,
		"media" : 2,
		"link" : 4,
		"poll" : 8,
		"question" : 16,
		"answered" : 32,
		"announcement" : 64,
		"contentComment" : 128,
		"bungieOfficial" : 256,
		"ninjaOfficial" : 512,
		"recruitment" : 1024
		"0" : "none",
		"1" : "textOnly",
		"2" : "media",
		"4" : "link",
		"8" : "poll",
		"16" : "question",
		"32" : "answered",
		"64" : "announcement",
		"128" : "contentComment",
		"256" : "bungieOfficial",
		"512" : "ninjaOfficial",
		"1024" : "recruitment"
	},
	"flags" : {
		"none" : 0,
		"bungieStaffPost" : 1,
		"forumNinjaPost" : 2,
		"forumMentorPost" : 4,
		"topicBungieStaffPosted" : 8,
		"topicBungieVolunteerPosted" : 16,
		"questionAnsweredByBungie" : 32,
		"questionAnsweredByNinja" : 64,
		"communityContent" : 128,
		"0" : "none",
		"1" : "bungieStaffPost",
		"2" : "forumNinjaPost",
		"4" : "forumMentorPost",
		"8" : "topicBungieStaffPosted",
		"16" : "topicBungieVolunteerPosted",
		"32" : "questionAnsweredByBungie",
		"64" : "questionAnsweredByninja",
		"128" : "communityContent"
	}
}